{
    "scenetype": "scene",
    "vmtype": "server",
    "aligntarget": "tag_align_kane_intro",
    "configstringfiletype": "scriptbundle",
    "dontthrottle": 1,
    "devstate": "placeholder",
    "nextscenemode": "init",
    "cameraswitcher": "c_bla_10_01_kaneintro_3rd_sh150_camera",
    "name": "cin_bla_10_01_kaneintro_3rd_sh150_female",
    "type": "scene",
    "nextscenebundle": "cin_bla_10_01_kaneintro_3rd_sh160",
    "igdtseqnum": 200,
    "objects": [
        {
            "model": "spawner_ally_hero_hendricks_blackstation",
            "player": 1,
            "vmtype": "server",
            "mainanim": "ch_bla_10_01_kaneintro_3rd_sh150_hendricks",
            "playerstance": "stand",
            "name": "hendricks",
            "type": "actor"
        },
        {
            "player": 1,
            "vmtype": "server",
            "model": "c_hro_playerfemale_egypt_fb",
            "mainanim": "pb_bla_10_01_kaneintro_3rd_sh150_playerfemale",
            "sharedigc": 1,
            "playerstance": "stand",
            "name": "new object 2",
            "type": "player"
        },
        {
            "player": 1,
            "vmtype": "server",
            "playerstance": "stand",
            "removeweapon": 1,
            "mainanim": "ch_bla_10_01_kaneintro_3rd_sh150_kane",
            "model": "spawner_ally_hero_rachel_blackstation",
            "name": "kane",
            "type": "actor"
        },
        {
            "type": "prop",
            "vmtype": "server",
            "playerstance": "stand",
            "takedamage": 1,
            "player": 1
        },
        {
            "type": "prop",
            "playerstance": "stand",
            "takedamage": 1,
            "player": 1,
            "vmtype": "server"
        },
        {
            "takedamage": 1,
            "type": "prop",
            "player": 1,
            "vmtype": "server",
            "playerstance": "stand"
        },
        {
            "type": "prop",
            "playerstance": "stand",
            "takedamage": 1,
            "player": 1,
            "vmtype": "server"
        },
        {
            "type": "prop",
            "playerstance": "stand",
            "takedamage": 1,
            "player": 1,
            "vmtype": "server"
        },
        {
            "type": "prop",
            "player": 1,
            "playerstance": "stand",
            "takedamage": 1,
            "vmtype": "server"
        },
        {
            "takedamage": 1,
            "type": "prop",
            "playerstance": "stand",
            "player": 1,
            "vmtype": "server"
        },
        {
            "playerstance": "stand",
            "type": "prop",
            "takedamage": 1,
            "player": 1,
            "vmtype": "server"
        },
        {
            "playerstance": "stand",
            "type": "prop",
            "player": 1,
            "vmtype": "server",
            "takedamage": 1
        },
        {
            "takedamage": 1,
            "playerstance": "stand",
            "player": 1,
            "vmtype": "server",
            "type": "prop"
        },
        {
            "takedamage": 1,
            "player": 1,
            "vmtype": "server",
            "type": "prop",
            "playerstance": "stand"
        },
        {
            "takedamage": 1,
            "player": 1,
            "vmtype": "server",
            "type": "prop",
            "playerstance": "stand"
        },
        {
            "playerstance": "stand",
            "player": 1,
            "vmtype": "server",
            "takedamage": 1,
            "type": "prop"
        },
        {
            "player": 1,
            "vmtype": "server",
            "playerstance": "stand",
            "type": "prop",
            "takedamage": 1
        },
        {
            "takedamage": 1,
            "player": 1,
            "vmtype": "server",
            "playerstance": "stand",
            "type": "prop"
        },
        {
            "player": 1,
            "vmtype": "server",
            "takedamage": 1,
            "type": "prop",
            "playerstance": "stand"
        },
        {
            "player": 1,
            "vmtype": "server",
            "playerstance": "stand",
            "takedamage": 1,
            "type": "prop"
        },
        {
            "type": "prop",
            "takedamage": 1,
            "player": 1,
            "vmtype": "server",
            "playerstance": "stand"
        },
        {
            "type": "prop",
            "player": 1,
            "takedamage": 1,
            "vmtype": "server",
            "playerstance": "stand"
        },
        {
            "type": "prop",
            "player": 1,
            "playerstance": "stand",
            "vmtype": "server",
            "takedamage": 1
        },
        {
            "player": 1,
            "type": "prop",
            "vmtype": "server",
            "playerstance": "stand",
            "takedamage": 1
        },
        {
            "type": "prop",
            "playerstance": "stand",
            "takedamage": 1,
            "player": 1,
            "vmtype": "server"
        },
        {
            "type": "prop",
            "playerstance": "stand",
            "player": 1,
            "vmtype": "server",
            "takedamage": 1
        },
        {
            "type": "prop",
            "playerstance": "stand",
            "takedamage": 1,
            "player": 1,
            "vmtype": "server"
        },
        {
            "type": "prop",
            "playerstance": "stand",
            "takedamage": 1,
            "player": 1,
            "vmtype": "server"
        },
        {
            "type": "prop",
            "playerstance": "stand",
            "takedamage": 1,
            "player": 1,
            "vmtype": "server"
        },
        {
            "playerstance": "stand",
            "takedamage": 1,
            "type": "prop",
            "player": 1,
            "vmtype": "server"
        },
        {
            "type": "prop",
            "playerstance": "stand",
            "takedamage": 1,
            "player": 1,
            "vmtype": "server"
        }
    ]
}